d3r/__init__.py
d3r/blastnfilter.py
d3r/celppreports.py
d3r/celpprunner.py
d3r/chimera_proteinligprep.py
d3r/evaluate.py
d3r/genchallengedata.py
d3r/getchallengedata.py
d3r/glidedocking.py
d3r/molfilevalidator.py
d3r/no_prot_omega_lig_prep.py
d3r/oefreddocking.py
d3r/packdockingresults.py
d3r/post_evaluation.py
d3r/postanalysis.py
d3r/proteinligprep.py
d3r/vinadocking.py
d3r/blast/__init__.py
d3r/blast/base.py
d3r/blast/hit.py
d3r/blast/hit_sequence.py
d3r/blast/ligand.py
d3r/blast/mcss.py
d3r/blast/parse_alignment.py
d3r/blast/query.py
d3r/celpp/__init__.py
d3r/celpp/blastnfilter.py
d3r/celpp/challengedata.py
d3r/celpp/chimeraprep.py
d3r/celpp/dataimport.py
d3r/celpp/evaluation.py
d3r/celpp/extsubmission.py
d3r/celpp/filetransfer.py
d3r/celpp/glide.py
d3r/celpp/makeblastdb.py
d3r/celpp/participant.py
d3r/celpp/postevaluation.py
d3r/celpp/proteinligprep.py
d3r/celpp/task.py
d3r/celpp/util.py
d3r/celpp/vina.py
d3r/celppade/__init__.py
d3r/celppade/custom_dock.py
d3r/celppade/custom_ligand_prep.py
d3r/celppade/custom_protein_prep.py
d3r/filter/__init__.py
d3r/filter/filter.py
d3r/filter/filtering_sets.py
d3r/utilities/__init__.py
d3r/utilities/align.py
d3r/utilities/analysis.py
d3r/utilities/challenge_data.py
d3r/utilities/in_put.py
d3r/utilities/io_parser.py
d3r/utilities/out_put.py
d3r/utilities/readers.py
d3r/utilities/run.py
d3r/utilities/writers.py
d3r-1.12.0.data/scripts/blastnfilter.py
d3r-1.12.0.data/scripts/celppreports.py
d3r-1.12.0.data/scripts/celpprunner.py
d3r-1.12.0.data/scripts/chimera_proteinligprep.py
d3r-1.12.0.data/scripts/evaluate.py
d3r-1.12.0.data/scripts/genchallengedata.py
d3r-1.12.0.data/scripts/getchallengedata.py
d3r-1.12.0.data/scripts/glidedocking.py
d3r-1.12.0.data/scripts/molfilevalidator.py
d3r-1.12.0.data/scripts/packdockingresults.py
d3r-1.12.0.data/scripts/post_evaluation.py
d3r-1.12.0.data/scripts/postanalysis.py
d3r-1.12.0.data/scripts/proteinligprep.py
d3r-1.12.0.dist-info/DESCRIPTION.rst
d3r-1.12.0.dist-info/METADATA
d3r-1.12.0.dist-info/RECORD
d3r-1.12.0.dist-info/WHEEL
d3r-1.12.0.dist-info/metadata.json
d3r-1.12.0.dist-info/top_level.txt
