Metadata-Version: 2.0
Name: d3r
Version: 1.12.0
Summary: Drug Design Data Resource CELPP Runner is an application to run the filtering, docking, and evaluation of new sequences from wwpdb
Home-page: https://github.com/drugdata/D3R
Author: Christopher Churas <churas@ncmir.ucsd.edu>,Shuai Liu <shuailiu25@gmail.com>,Jeff Wagner <j5wagner@ucsd.edu>,Rob Swift <rvswift@ucsd.edu>
Author-email: drugdesigndata@gmail.com
License: Other
Keywords: d3r
Platform: UNKNOWN
Classifier: Development Status :: 2 - Pre-Alpha
Classifier: Intended Audience :: Science/Research
Classifier: License :: Free for non-commercial use
Classifier: Natural Language :: English
Classifier: Environment :: Console
Classifier: Programming Language :: Python :: 2.6
Classifier: Programming Language :: Python :: 2.7
Classifier: Topic :: Scientific/Engineering :: Chemistry
Requires-Dist: argparse
Requires-Dist: biopython (==1.68)
Requires-Dist: configparser
Requires-Dist: easywebdav
Requires-Dist: ftpretty
Requires-Dist: lockfile
Requires-Dist: psutil
Requires-Dist: python-dateutil
Requires-Dist: requests
Requires-Dist: xlsxwriter
